atlasctf_21_prod_29
