Metadata-Version: 2.1
Name: atlasctf_21_prod_29
Version: 9.9
Summary: Fake internal package
